_sargasso.cp311-win_amd64.pyd
sargasso/__init__.py
sargasso-0.5.1.data/platlib/flang-b230c7bcadeb39f3e7e9de6d960b856d.dll
sargasso-0.5.1.data/platlib/flangrti-95c9d3d60053a668e99fd30038f11ce0.dll
sargasso-0.5.1.data/platlib/libomp-23f42654910d405a7852cc2a9abb4fa3.dll
sargasso-0.5.1.data/platlib/msvcp140-f3a4bc3af4ab149c831da2c39e62f8fa.dll
sargasso-0.5.1.data/platlib/openblas-847a4898def0f371ab675fd5e83d963e.dll
sargasso-0.5.1.dist-info/DELVEWHEEL
sargasso-0.5.1.dist-info/METADATA
sargasso-0.5.1.dist-info/RECORD
sargasso-0.5.1.dist-info/top_level.txt
sargasso-0.5.1.dist-info/WHEEL
