Metadata-Version: 2.1
Name: sargasso
Version: 0.5.1
Requires-Python: >=3.9
Requires-Dist: numpy >=1.18
Requires-Dist: pybind11 >=2.6
